<?xml version="1.0" encoding="UTF-8" ?>
<myopenmath id="1059257">
<statement>
<figure><image source="https://myopenmaths3.s3.amazonaws.com/gimgs/7122dac4fece282dc77a1ef0ade66eb7.png" /></figure><p>A triangle. Going around counterclockwise, an angle is labeled A  and its opposite side is labeled a=35. An angle is labeled B  and its opposite side is labeled b=56. An angle is labeled C  and its opposite side is labeled c=51.</p>
<p>Solve the triangle</p>
<p>
<m>\displaystyle{A}=</m> <fillin characters="7" />° </p>
<p>
<m>\displaystyle{B}=</m> <fillin characters="7" />° </p>
<p>
<m>\displaystyle{C}=</m> <fillin characters="7" />°
</p>
<p>Round to 2 decimal places.</p>
</statement>
<solution>
<p><ul><li><p>37.82</p></li><li><p>78.86</p></li><li><p>63.32</p></li></ul></p>
</solution>
</myopenmath>

