<?xml version="1.0" encoding="utf-8"?>
<myopenmath xmlns:pi="http://pretextbook.org/2020/pretext/internal" id="3419">
<statement>
<p>
Solve the equation for the given variable:</p>
<p>
<m>\displaystyle{\left(-{2}{z}-{4}\right)}={7}</m></p>
<p>
If your answer is a fraction, write it in fraction from and reduce it completely. Do NOT convert to decimals.</p>
<p>
<m>\displaystyle{z}</m> = <fillin characters="8" />   
</p>
</statement>
<solution>
<p><ul><li><m>\displaystyle-\frac{{11}}{{2}}</m></li></ul></p>
</solution>
</myopenmath>

