<?xml version="1.0" encoding="utf-8"?>
<myopenmath xmlns:pi="http://pretextbook.org/2020/pretext/internal" id="900186">
<statement>
<p>The diagram below shows a triangle inscribed in a rectangle. The rectangle has width <m>\displaystyle{8.00}</m> and height <m>\displaystyle{6.00}</m>. One side of the triangle is a long side of the rectangle. The other triangle sides have lengths <m>\displaystyle{6.32}</m> and <m>\displaystyle{8.49}</m>.</p><image width="67%"  pi:generated="problems/images/388d1ffc7f4dd833de5c5847696d281b.png" /><p>
  What is the area of the shaded inscribed triangle? <fillin characters="4" /> in²
  </p>
<p>
  What is the area of the rectangle? <fillin characters="4" /> in²
  </p>
<p>
  What is the area of the unshaded parts of the rectangle? <fillin characters="4" /> in²</p>

</statement>
<solution>
<p><ul><li>24.0</li><li>48.0</li><li>24.0</li></ul></p>
</solution>
</myopenmath>

