<?xml version="1.0" encoding="utf-8"?>
<myopenmath xmlns:pi="http://pretextbook.org/2020/pretext/internal" id="102032">
<statement>
<p>
Write a function describing the relationship of the given variables.</p>
<p>
<m>\displaystyle{W}</m> varies inversely with the square of <m>\displaystyle{n}</m> and when <m>\displaystyle{n}={6}</m>, <m>\displaystyle{W}={2}</m></p>
<p>
<m>\displaystyle{W}=</m><fillin characters="20" />  

</p>
</statement>
<solution>
<p><ul><li><m>\displaystyle\frac{{72}}{{n}^{{2}}}</m></li></ul></p>
</solution>
</myopenmath>

