<?xml version='1.0' encoding='utf-8'?>
<myopenmath xmlns:pi="http://pretextbook.org/2020/pretext/internal" id="1446161">
<statement>
<p>Calculate how far a plane flying at 90 nm/hour would travel in 2.4 hours. <input type="text" style="width:25ch" name="qn0" id="qn0" value="" autocomplete="off" aria-label="Question 1" class="text"/></p>

</statement>
<solution>
<p><ul><li>216</li></ul></p><p>The ratio (nm/hour) suggests that we can multiply by hours to determine distance (nautical miles or nm).</p>
<p><m>\displaystyle\frac{{{90}\ \text{ nm}}}{{{1}\ \text{ hr}}}\cdot{2.4}\ \text{ hr}={216}\ \text{ nm}</m></p>
<p>We could also change the ratio to be in terms of 2.4 hours.</p>
<p><m>\displaystyle\frac{{{90}\ \text{ nm}}}{{{1}\ \text{ hr}}}\cdot\frac{{{2.4}}}{{{2.4}}}=\frac{{{216}\ \text{  nm}}}{{{2.4}\ \text{ hr}}}</m>.</p>
</solution>
</myopenmath>