<?xml version='1.0' encoding='utf-8'?>
<myopenmath xmlns:pi="http://pretextbook.org/2020/pretext/internal" id="1548930">
<statement>
<p>Laura invested <dollar/>5,700 in stocks and later sold them for <dollar/>7,200. The sale price is what percent of the purchase price? <input type="text" style="width:8.2ch" name="qn0" id="qn0" value="" autocomplete="off" aria-label="Question 1" class="text"/> <percent/></p>
<p>Round to 2 decimal places.</p>


</statement>
<solution>
<p><ul><li>126.32</li></ul></p><p>The percent we desire is new/old.</p>
<p><m>\displaystyle\frac{{\${7},{200}}}{{\${5},{700}}}={1.2631578947368}</m></p>
<p>
  <m>\displaystyle{100}\times{1.2631578947368}={126.31578947368}</m><percent/></p>
<p>
  <m>\displaystyle{126.31578947368}\%\approx{126.32}\%</m></p>
<p>The percent is greater than 100, because the value increased. It is all of the original value plus more.</p>
</solution>
</myopenmath>