<?xml version='1.0' encoding='utf-8'?>
<myopenmath xmlns:pi="http://pretextbook.org/2020/pretext/internal" id="591886">
<statement>
<p>206 in. to yards, feet, and inches</p>
<p><input type="text" style="width:3.4ch" name="qn1000" id="qn1000" value="" autocomplete="off" aria-label="Question 1 Part 1 of 3" class="text"/> yds <input type="text" style="width:3.4ch" name="qn1001" id="qn1001" value="" autocomplete="off" aria-label="Question 1 Part 2 of 3" class="text"/> ft <input type="text" style="width:3.4ch" name="qn1002" id="qn1002" value="" autocomplete="off" aria-label="Question 1 Part 3 of 3" class="text"/> in</p>

</statement>
<solution>
<p><ul><li>5</li><li>2</li><li>2</li></ul></p>
</solution>
</myopenmath>