<?xml version="1.0" encoding="utf-8"?>
<myopenmath xmlns:pi="http://pretextbook.org/2020/pretext/internal" id="102026">
<statement>
<p>
Write a function describing the relationship of the given variables.</p>
<p>
<m>\displaystyle{y}</m> varies directly with the square of <m>\displaystyle{x}</m> and when <m>\displaystyle{x}={2}</m>, <m>\displaystyle{y}={16}</m></p>
<p>
<m>\displaystyle{y}=</m><fillin characters="20" />  

</p>
</statement>
<solution>
<p><ul><li><m>\displaystyle{4}\cdot{x}^{{2}}</m></li></ul></p>
</solution>
</myopenmath>

