<?xml version="1.0" encoding="utf-8"?>
<myopenmath xmlns:pi="http://pretextbook.org/2020/pretext/internal" id="392038">
<statement>
<p>
Solve: <m>\displaystyle{{\log}_{{5}}{\left({q}\right)}}={2}</m>
</p>
<p>Give an exact answer. Simplify as much as possible.
</p>
<p><m>\displaystyle{q}=</m><fillin characters="20" />
</p>
</statement>
<solution>
<p><ul><li>25</li></ul></p><p>Solve: <m>\displaystyle{{\log}_{{5}}{\left({q}\right)}}={2}</m>
Rewrite as exponential equation : <m>\displaystyle{5}^{{2}}={q}</m>
</p>
<p>So : <m>\displaystyle{q}={25}</m>
</p>
</solution>
</myopenmath>

