<?xml version="1.0" encoding="utf-8"?>
<myopenmath xmlns:pi="http://pretextbook.org/2020/pretext/internal" id="1471177">
<statement>
<image width="33%"  pi:generated="problems/images/15b12606e0fc6abd3472a51b0916152d.png" />
<p>Find the perimeter and area of the triangle above. Side lengths are measurements.</p>
<p>perimeter = <fillin characters="6" /></p>
<p>area = <fillin characters="6" /></p>

</statement>
<solution>
<p><ul><li>11.2</li><li>3.14</li></ul></p><p>The perimeter is the sum of the three sides which are given. <m>\displaystyle{5.33}+{2.82}+{3.01}={11.16}</m>.</p>
<p>The area is given by <m>\displaystyle\frac{{1}}{{2}}{b}{h}=\frac{{1}}{{2}}{5.33}\cdot{1.18}={3.1447}\approx{3.14}</m>.</p>
</solution>
</myopenmath>

