<?xml version="1.0" encoding="utf-8"?>
<myopenmath xmlns:pi="http://pretextbook.org/2020/pretext/internal" id="1460720">
<statement>
<p>Determine whether each person's salaries followed a linear or an exponential growth pattern.</p>
<table><tabular> <row><cell>Year</cell><cell>Patrisse</cell><cell>Randall</cell><cell>Bisa</cell></row><row><cell>2019</cell><cell>65725</cell><cell>44287</cell><cell>53393.26</cell></row><row><cell>2020</cell><cell>68354</cell><cell>46058.48</cell><cell>56415.52</cell></row><row><cell>2021</cell><cell>71088.16</cell><cell>47900.82</cell><cell>59437.78</cell></row><row><cell>2022</cell><cell>73931.69</cell><cell>49816.85</cell><cell>62460.04</cell></row><row><cell>2023</cell><cell>76888.95</cell><cell>51809.53</cell><cell>65482.3</cell></row><row><cell>2024</cell><cell>79964.51</cell><cell>53881.91</cell><cell>68504.56</cell></row></tabular></table>
<p>Patrisse: </p>
<p><ol style="list-style-type:upper-alpha"><li>linear</li> 
<li>exponential</li> 
</ol></p>
<p>Randall: </p>
<p><ol style="list-style-type:upper-alpha"><li>linear</li> 
<li>exponential</li> 
</ol></p>
<p>Bisa: </p>
<p><ol style="list-style-type:upper-alpha"><li>linear</li> 
<li>exponential</li> 
</ol></p>


</statement>
<solution>
<p><ul><li>B: exponential</li><li>B: exponential</li><li>A: linear</li></ul></p>
</solution>
</myopenmath>

