<?xml version="1.0" encoding="utf-8"?>
<myopenmath xmlns:pi="http://pretextbook.org/2020/pretext/internal" id="965">
<statement>
<p>
Identify as an increase or decrease.  Then find the percent of increase or decrease.  If necessary, round to the nearest percent.</p>
<p>
<em>Original:</em>  120</p>
<p>
<em> New:</em> 190</p>
<p>
<fillin characters="5" /><percent/> </p>
<p><ol style="list-style-type:upper-alpha"><li>Increasing</li> 
<li>Decreasing</li> 
</ol></p>


</statement>
<solution>
<p><ul><li>58</li><li>A: Increasing</li></ul></p>
</solution>
</myopenmath>

