<?xml version="1.0" encoding="utf-8"?>
<myopenmath xmlns:pi="http://pretextbook.org/2020/pretext/internal" id="1435286">
<statement>
<image width="33%"  pi:generated="problems/images/f967e85c3613b58ac143540fb48b9904.png" /><p>
Suppose the legs have lengths <m>\displaystyle{a}={119}</m> and <m>\displaystyle{b}={120}</m>.</p>
<p>
Answers must be exact results (fractions).</p>
<p>
<m>\displaystyle{\sin{{\left({A}\right)}}}=</m> <fillin characters="20" />   </p>
<p>
<m>\displaystyle{\cos{{\left({A}\right)}}}=</m> <fillin characters="20" />   </p>
<p>
<m>\displaystyle{\tan{{\left({A}\right)}}}=</m> <fillin characters="20" />   </p>
<p>
<m>\displaystyle{\sec{{\left({A}\right)}}}=</m> <fillin characters="20" />   </p>
<p>
<m>\displaystyle{\csc{{\left({A}\right)}}}=</m> <fillin characters="20" />   </p>
<p>
<m>\displaystyle{\cot{{\left({A}\right)}}}=</m> <fillin characters="20" />   
</p>
</statement>
<solution>
<p><ul><li><m>\displaystyle\frac{{119}}{{169}}</m></li><li><m>\displaystyle\frac{{120}}{{169}}</m></li><li><m>\displaystyle\frac{{119}}{{120}}</m></li><li><m>\displaystyle\frac{{169}}{{120}}</m></li><li><m>\displaystyle\frac{{169}}{{119}}</m></li><li><m>\displaystyle\frac{{120}}{{119}}</m></li></ul></p>
</solution>
</myopenmath>

