<?xml version="1.0" encoding="utf-8"?>
<myopenmath xmlns:pi="http://pretextbook.org/2020/pretext/internal" id="3600">
<statement>
<p>
The function below has the form <m>\displaystyle{f{{\left({x}\right)}}}={b}^{{x}}+{k}</m>.</p><image width="33%"  pi:generated="problems/images/446719db07ea95c7f3580b6eb56d37af.png" />
<p>
Which of the following functions is shown on the graph?
</p>
<p><ol style="list-style-type:upper-alpha"><li><m>\displaystyle{f{{\left({x}\right)}}}={\left(\frac{{1}}{{5}}\right)}^{{x}}-{3}</m></li> 
<li><m>\displaystyle{f{{\left({x}\right)}}}={\left(\frac{{1}}{{5}}\right)}^{{x}}-{4}</m></li> 
<li><m>\displaystyle{f{{\left({x}\right)}}}={5}^{{x}}-{3}</m></li> 
<li><m>\displaystyle{f{{\left({x}\right)}}}={5}^{{x}}-{4}</m></li> 
<li><m>\displaystyle{f{{\left({x}\right)}}}={\left(\frac{{1}}{{5}}\right)}^{{x}}+{3}</m></li> 
<li><m>\displaystyle{f{{\left({x}\right)}}}={\left(\frac{{1}}{{5}}\right)}^{{x}}-{2}</m></li> 
<li><m>\displaystyle{f{{\left({x}\right)}}}={5}^{{x}}+{3}</m></li> 
<li><m>\displaystyle{f{{\left({x}\right)}}}={5}^{{x}}-{2}</m></li> 
</ol></p>


</statement>
<solution>
<p><ul><li>A: <m>\displaystyle{f{{\left({x}\right)}}}={\left(\frac{{1}}{{5}}\right)}^{{x}}-{3}</m></li></ul></p>
</solution>
</myopenmath>

