<?xml version="1.0" encoding="utf-8"?>
<myopenmath xmlns:pi="http://pretextbook.org/2020/pretext/internal" id="1471129">
<statement>
<image width="33%"  pi:generated="problems/images/a3cc5c993ad202a40b3b7f4c11875c55.png" />
<p>Find the perimeter and area of the trapezoid above. Side lengths are measurements.</p>
<p>perimeter = <fillin characters="6" /></p>
<p>area = <fillin characters="6" /></p>

</statement>
<solution>
<p><ul><li>38.43</li><li>81.0</li></ul></p><p>The perimeter is the sum of the four sides which are given. <m>\displaystyle{12.77}+{8.92}+{9.23}+{7.51}={38.43}</m>.</p>
<p>The area is given by <m>\displaystyle\frac{{1}}{{2}}{\left({a}+{b}\right)}=\frac{{1}}{{2}}{\left({12.77}+{9.23}\right)}={80.96}\approx{81}</m>.</p>
</solution>
</myopenmath>

