<?xml version="1.0" encoding="utf-8"?>
<myopenmath xmlns:pi="http://pretextbook.org/2020/pretext/internal" id="838276">
<statement>
<p>
Which of the following graphs is the correct plot of <m>\displaystyle{y}={6}{\sin{{\left({5}{x}\right)}}}</m>?</p><image width="33%"  pi:generated="problems/images/c6acd7a1b25fd28bb4271063b08824a6.png" />
<image width="33%"  pi:generated="problems/images/cb3122f628db44485f2287802f171c52.png" />
<image width="33%"  pi:generated="problems/images/6d3eec642b77a41228057c12246148d2.png" />
<image width="33%"  pi:generated="problems/images/f637c53b895869fb58ce150a225b36bd.png" />

</statement>
<solution>
<p><ul><li>C: <image width="33%"  pi:generated="problems/images/6d3eec642b77a41228057c12246148d2.png" />
</li></ul></p>
</solution>
</myopenmath>

