<?xml version="1.0" encoding="utf-8"?>
<myopenmath xmlns:pi="http://pretextbook.org/2020/pretext/internal" id="3097">
<statement>
<p>
A quadratic function has its vertex at the point <m>\displaystyle{\left(-{5},-{7}\right)}</m>.  The function
passes through the point <m>\displaystyle{\left({3},-{1}\right)}</m>.  Find the expanded form of the function.
</p>
<p>
The coefficient <m>\displaystyle{a}</m> is  <fillin characters="10" />   . </p>
<p>
The coefficient <m>\displaystyle{b}</m> is <fillin characters="10" />   . </p>
<p>
The constant term <m>\displaystyle{c}</m> is <fillin characters="10" />   .
</p>
</statement>
<solution>
<p><ul><li>0.09375</li><li>0.9375</li><li>-4.65625</li></ul></p>
</solution>
</myopenmath>

